morvba/__init__.py
morvba/cC.py
tests/__init__.py
tests/test_file.py
morvba-2.0.1.dist-info/LICENSE
morvba-2.0.1.dist-info/METADATA
morvba-2.0.1.dist-info/WHEEL
morvba-2.0.1.dist-info/top_level.txt
morvba-2.0.1.dist-info/RECORD
