Metadata-Version: 2.1
Name: morvba
Version: 2.0.1
Summary: A package providing VBA-like and other useful functions for Python.
Home-page: https://github.com/masterofrisk/pythonvba
Author: Carlos Martins
Author-email: c@tgrafi.co
Classifier: Development Status :: 5 - Production/Stable
Classifier: Intended Audience :: Developers
Classifier: License :: OSI Approved :: MIT License
Classifier: Programming Language :: Python :: 3
Classifier: Programming Language :: Python :: 3.6
Classifier: Programming Language :: Python :: 3.7
Classifier: Programming Language :: Python :: 3.8
Classifier: Programming Language :: Python :: 3.9
Classifier: Programming Language :: Python :: 3.10
Classifier: Programming Language :: Python :: 3.11
Requires-Python: >=3.6
License-File: LICENSE
Requires-Dist: chardet
Requires-Dist: colorama
Requires-Dist: configparser
Requires-Dist: python-dateutil
Requires-Dist: tiktoken
